datatoolkit/__init__.py
datatoolkit/admin.py
datatoolkit/apps.py
datatoolkit/models.py
datatoolkit/tests.py
datatoolkit/urls.py
datatoolkit/views.py
datatoolkit/migrations/__init__.py
django_data_toolkit-0.1.0.dist-info/LICENSE
django_data_toolkit-0.1.0.dist-info/METADATA
django_data_toolkit-0.1.0.dist-info/WHEEL
django_data_toolkit-0.1.0.dist-info/top_level.txt
django_data_toolkit-0.1.0.dist-info/RECORD
